{
  "project_info": {
    "project_number": "445918286870",
    "firebase_url": "https://bilgram-9e58a.firebaseio.com",
    "project_id": "bilgram-9e58a",
    "storage_bucket": "bilgram-9e58a.appspot.com"
  },
  "client": [
    {
      "client_info": {
        "mobilesdk_app_id": "1:445918286870:android:d851dc3dd15f3090",
        "android_client_info": {
          "package_name": "com.mert.bilgram"
        }
      },
      "oauth_client": [
        {
          "client_id": "445918286870-cj5rhjcg9mgp4cuf32ndrn3ojdjdugmt.apps.googleusercontent.com",
          "client_type": 1,
          "android_info": {
            "package_name": "com.mert.bilgram",
            "certificate_hash": "02f0601031b282907792a5e52d6417c2598ab6b1"
          }
        },
        {
          "client_id": "445918286870-iq2mh4c4r0amic0sh0tfjs2hajtafnrh.apps.googleusercontent.com",
          "client_type": 3
        }
      ],
      "api_key": [
        {
          "current_key": "AIzaSyD2gGi6bnYDSEgyJuDAPYw3jBOdl9xY7ic"
        }
      ],
      "services": {
        "analytics_service": {
          "status": 1
        },
        "appinvite_service": {
          "status": 2,
          "other_platform_oauth_client": [
            {
              "client_id": "445918286870-iq2mh4c4r0amic0sh0tfjs2hajtafnrh.apps.googleusercontent.com",
              "client_type": 3
            }
          ]
        },
        "ads_service": {
          "status": 2
        }
      }
    }
  ],
  "configuration_version": "1"
}